{
    "fluentMethods": true,
    "clientRootFolder": "",
    "relationships": [
        {
            "relationshipName": "creator",
            "otherEntityName": "employee",
            "relationshipType": "many-to-one",
            "otherEntityField": "id"
        },
        {
            "relationshipName": "assigned",
            "otherEntityName": "employee",
            "relationshipType": "many-to-one",
            "otherEntityField": "id"
        }
    ],
    "fields": [
        {
            "fieldName": "workID",
            "fieldType": "Long"
        },
        {
            "fieldName": "title",
            "fieldType": "String"
        },
        {
            "fieldName": "description",
            "fieldType": "String"
        },
        {
            "fieldName": "createDate",
            "fieldType": "ZonedDateTime"
        },
        {
            "fieldName": "dueDate",
            "fieldType": "ZonedDateTime"
        },
        {
            "fieldName": "status",
            "fieldType": "String"
        },
        {
            "fieldName": "completionDate",
            "fieldType": "ZonedDateTime"
        },
        {
            "fieldName": "completionRemarks",
            "fieldType": "String"
        }
    ],
    "changelogDate": "20190305035802",
    "dto": "mapstruct",
    "searchEngine": false,
    "service": "serviceClass",
    "entityTableName": "work",
    "databaseType": "sql",
    "jpaMetamodelFiltering": false,
    "pagination": "no"
}
